<annotations><filename>frame_1719.jpg</filename><folder>images</folder><size><width>1280</width><height>720</height><depth>3</depth></size><object><name>hand</name><pose>Unspecified</pose><truncated>0</truncated><difficult>0</difficult><bndbox><xmin>204.0</xmin><ymin>390.0</ymin><xmax>376.0</xmax><ymax>565.0</ymax></bndbox></object><object><name>hand</name><pose>Unspecified</pose><truncated>0</truncated><difficult>0</difficult><bndbox><xmin>359.0</xmin><ymin>389.0</ymin><xmax>636.0</xmax><ymax>561.0</ymax></bndbox></object><object><name>hand</name><pose>Unspecified</pose><truncated>0</truncated><difficult>0</difficult><bndbox><xmin>624.0</xmin><ymin>414.0</ymin><xmax>884.0</xmax><ymax>609.0</ymax></bndbox></object><object><name>hand</name><pose>Unspecified</pose><truncated>0</truncated><difficult>0</difficult><bndbox><xmin>194.0</xmin><ymin>575.0</ymin><xmax>408.0</xmax><ymax>707.0</ymax></bndbox></object></annotations>