<annotations><filename>frame_0914.jpg</filename><folder>images</folder><size><width>1280</width><height>720</height><depth>3</depth></size><object><name>hand</name><pose>Unspecified</pose><truncated>0</truncated><difficult>0</difficult><bndbox><xmin>395.0</xmin><ymin>79.0</ymin><xmax>595.0</xmax><ymax>245.0</ymax></bndbox></object><object><name>hand</name><pose>Unspecified</pose><truncated>0</truncated><difficult>0</difficult><bndbox><xmin>594.0</xmin><ymin>107.0</ymin><xmax>829.0</xmax><ymax>259.0</ymax></bndbox></object><object><name>hand</name><pose>Unspecified</pose><truncated>0</truncated><difficult>0</difficult><bndbox><xmin>488.0</xmin><ymin>486.0</ymin><xmax>925.0</xmax><ymax>709.0</ymax></bndbox></object></annotations>