<annotations><filename>frame_1863.jpg</filename><folder>images</folder><size><width>1280</width><height>720</height><depth>3</depth></size><object><name>hand</name><pose>Unspecified</pose><truncated>0</truncated><difficult>0</difficult><bndbox><xmin>133.0</xmin><ymin>347.00000000000006</ymin><xmax>304.0</xmax><ymax>486.00000000000006</ymax></bndbox></object><object><name>hand</name><pose>Unspecified</pose><truncated>0</truncated><difficult>0</difficult><bndbox><xmin>439.0</xmin><ymin>388.99999999999994</ymin><xmax>646.0</xmax><ymax>529.0</ymax></bndbox></object><object><name>hand</name><pose>Unspecified</pose><truncated>0</truncated><difficult>0</difficult><bndbox><xmin>725.0</xmin><ymin>559.0</ymin><xmax>956.0</xmax><ymax>696.0</ymax></bndbox></object><object><name>hand</name><pose>Unspecified</pose><truncated>0</truncated><difficult>0</difficult><bndbox><xmin>328.0</xmin><ymin>582.0</ymin><xmax>564.0</xmax><ymax>703.0</ymax></bndbox></object></annotations>