<annotations><filename>frame_1947 (2).jpg</filename><folder>images</folder><size><width>1280</width><height>720</height><depth>3</depth></size><object><name>hand</name><pose>Unspecified</pose><truncated>0</truncated><difficult>0</difficult><bndbox><xmin>189.0</xmin><ymin>588.0</ymin><xmax>430.0</xmax><ymax>706.0</ymax></bndbox></object><object><name>hand</name><pose>Unspecified</pose><truncated>0</truncated><difficult>0</difficult><bndbox><xmin>153.0</xmin><ymin>403.0</ymin><xmax>371.0</xmax><ymax>617.0</ymax></bndbox></object><object><name>hand</name><pose>Unspecified</pose><truncated>0</truncated><difficult>0</difficult><bndbox><xmin>436.0</xmin><ymin>352.99999999999994</ymin><xmax>614.0</xmax><ymax>519.0</ymax></bndbox></object><object><name>hand</name><pose>Unspecified</pose><truncated>0</truncated><difficult>0</difficult><bndbox><xmin>716.0</xmin><ymin>512.0</ymin><xmax>961.0</xmax><ymax>682.0</ymax></bndbox></object></annotations>